ckipneutools/__init__.py
ckipneutools-0.0.11.dist-info/METADATA
ckipneutools-0.0.11.dist-info/WHEEL
ckipneutools-0.0.11.dist-info/top_level.txt
ckipneutools-0.0.11.dist-info/RECORD
